fastapi_bootstrap/__init__.py
fastapi_bootstrap/auth.py
fastapi_bootstrap/base.py
fastapi_bootstrap/logging_api_route.py
fastapi_bootstrap/py.typed
fastapi_bootstrap/response.py
fastapi_bootstrap/exception/__init__.py
fastapi_bootstrap/exception/definition.py
fastapi_bootstrap/exception/error_info.py
fastapi_bootstrap/exception/handler.py
fastapi_bootstrap/exception/type.py
fastapi_bootstrap/log/__init__.py
fastapi_bootstrap/log/setup.py
fastapi_bootstrap/type/__init__.py
fastapi_bootstrap/type/base_model.py
fastapi_bootstrap/util/__init__.py
fastapi_bootstrap/util/etc.py
fastapi_bootstrap/util/identifier.py
fastapi_bootstrap-0.1.1.dist-info/licenses/LICENSE
fastapi_bootstrap-0.1.1.dist-info/METADATA
fastapi_bootstrap-0.1.1.dist-info/WHEEL
fastapi_bootstrap-0.1.1.dist-info/top_level.txt
fastapi_bootstrap-0.1.1.dist-info/RECORD
