Metadata-Version: 2.4
Name: fastapi_bootstrap
Version: 0.1.1
Summary: 🚀 Easy FastAPI Setup Kit - Production-ready FastAPI boilerplate with logging, error handling, and more
Author-email: JunSeok Kim <infend@gmail.com>
License: MIT
Project-URL: Homepage, https://github.com/bestend/fastapi_bootstrap
Project-URL: Documentation, https://github.com/bestend/fastapi_bootstrap#readme
Project-URL: Repository, https://github.com/bestend/fastapi_bootstrap.git
Project-URL: Issues, https://github.com/bestend/fastapi_bootstrap/issues
Keywords: fastapi,logging,error-handling,api,web,framework,production
Classifier: Development Status :: 3 - Alpha
Classifier: Intended Audience :: Developers
Classifier: License :: OSI Approved :: MIT License
Classifier: Programming Language :: Python :: 3
Classifier: Programming Language :: Python :: 3.12
Classifier: Programming Language :: Python :: 3.13
Classifier: Framework :: FastAPI
Classifier: Topic :: Software Development :: Libraries :: Python Modules
Requires-Python: >=3.12
License-File: LICENSE
Requires-Dist: fastapi>=0.100.0
Requires-Dist: uvicorn>=0.20.0
Requires-Dist: pydantic>=2.0.0
Requires-Dist: loguru>=0.7.0
Requires-Dist: opentelemetry-api>=1.20.0
Requires-Dist: PyYAML>=6.0
Provides-Extra: auth
Requires-Dist: python-jose[cryptography]>=3.3.0; extra == "auth"
Requires-Dist: httpx>=0.24.0; extra == "auth"
Provides-Extra: dev
Requires-Dist: pytest>=7.0.0; extra == "dev"
Requires-Dist: pytest-cov>=4.0.0; extra == "dev"
Requires-Dist: pytest-asyncio>=0.21.0; extra == "dev"
Requires-Dist: pytest-mock>=3.10.0; extra == "dev"
Requires-Dist: httpx>=0.24.0; extra == "dev"
Requires-Dist: ruff>=0.1.0; extra == "dev"
Requires-Dist: mypy>=1.0.0; extra == "dev"
Requires-Dist: types-PyYAML>=6.0.0; extra == "dev"
Requires-Dist: python-jose[cryptography]>=3.3.0; extra == "dev"
Dynamic: license-file
